ntlm3/__init__.py
ntlm3/compat.py
ntlm3/des.py
ntlm3/des_c.py
ntlm3/des_data.py
ntlm3/HTTPNtlmAuthHandler.py
ntlm3/ntlm.py
ntlm3/U32.py
python_ntlm3-1.0.2.dist-info/DESCRIPTION.rst
python_ntlm3-1.0.2.dist-info/METADATA
python_ntlm3-1.0.2.dist-info/metadata.json
python_ntlm3-1.0.2.dist-info/RECORD
python_ntlm3-1.0.2.dist-info/top_level.txt
python_ntlm3-1.0.2.dist-info/WHEEL
